[
    {
        "device_id": "device123",
        "key": "key12345",
        "expirydate": "31-12-2025",
        "Allowoffline": true
    },
    {
        "device_id": "device456",
        "key": "key67890",
        "expirydate": "15-06-2025",
        "Allowoffline": false
    },
    {
        "device_id": "dd6df0a51ceefe11",
        "key": "amir3",
        "expirydate": "15-06-9999",
        "Allowoffline": false
    },
    {
        "device_id": "fd1005f8900e767a",
        "key": "mordad",
        "expirydate": "13-03-2026",
        "Allowoffline": false
    },
    {
        "device_id": "706959d0d0c0e504",
        "key": "Arman",
        "expirydate": "13-03-9999",
        "Allowoffline": false
    },
    {
        "device_id": "539d03bae22ea2e3",
        "key": "AliWer",
        "expirydate": "28-02-2026",
        "Allowoffline": false
    }
]
